[
  {
    "Name": "Backup1",
    "SourceFilePath": "C:\\Users\\hugob\\Desktop\\Source\\uzvisqhbd - Copie.txt",
    "TargetFilePath": "C:\\Users\\hugob\\Desktop\\Destination\\20250212094245\\uzvisqhbd - Copie.txt",
    "State": "END",
    "TotalFilesToCopy": 5,
    "TotalFilesSize": 65,
    "NbFilesLeftToDo": 0,
    "Progression": 100
  },
  {
    "Name": "test",
    "SourceFilePath": "C:\\Users\\eloia\\Documents\\Maxime\\Source\\dsfsdf.txt",
    "TargetFilePath": "C:\\Users\\eloia\\Documents\\Maxime\\Destination\\20250212091022\\dsfsdf.txt",
    "State": "END",
    "TotalFilesToCopy": 1,
    "TotalFilesSize": 13,
    "NbFilesLeftToDo": 0,
    "Progression": 100
  }
]